dep_guardian/__init__.py
dep_guardian/__version__.py
dep_guardian/cli.py
dep_guardian/package-lock.json
dep_guardian/package.json
dep_guardian/semver_checker.js
dep_guardian/gui/__init__.py
dep_guardian/gui/app.py
dep_guardian/gui/templates/index.html
dep_guardian/gui/templates/llm_analysis_result.html
dep_guardian/gui/templates/report_display.html
dep_guardian-0.2.5.dist-info/licenses/LICENSE
dep_guardian-0.2.5.dist-info/METADATA
dep_guardian-0.2.5.dist-info/WHEEL
dep_guardian-0.2.5.dist-info/entry_points.txt
dep_guardian-0.2.5.dist-info/top_level.txt
dep_guardian-0.2.5.dist-info/RECORD
