Metadata-Version: 2.4
Name: dep-guardian
Version: 0.2.5
Summary: CLI tool to audit & auto-update Node.js dependencies, with AI insights.
Home-page: https://github.com/AbhayBhandarkar/DepGuardian
Author: Abhay Bhandarkar
License: MIT
Project-URL: Bug Reports, https://github.com/AbhayBhandarkar/DepGuardian/issues
Project-URL: Source, https://github.com/AbhayBhandarkar/DepGuardian
Keywords: npm dependency audit security vulnerability update automation github osv gui flask llm gemini agentic
Classifier: Development Status :: 4 - Beta
Classifier: Intended Audience :: Developers
Classifier: Topic :: Software Development :: Build Tools
Classifier: Topic :: System :: Software Distribution
Classifier: License :: OSI Approved :: MIT License
Classifier: Programming Language :: Python :: 3
Classifier: Programming Language :: Python :: 3.9
Classifier: Programming Language :: Python :: 3.10
Classifier: Programming Language :: Python :: 3.11
Classifier: Environment :: Console
Classifier: Environment :: Web Environment
Classifier: Operating System :: OS Independent
Classifier: Framework :: Flask
Requires-Python: >=3.9
License-File: LICENSE
Requires-Dist: click<9.0,>=8.0
Requires-Dist: requests<3.0,>=2.25
Requires-Dist: packaging<24.0,>=21.0
Requires-Dist: GitPython<4.0,>=3.1
Requires-Dist: PyGithub<2.0,>=1.55
Requires-Dist: Flask>=2.0.0
Requires-Dist: werkzeug>=2.0.0
Requires-Dist: httpx<0.28.0,>=0.23.0
Requires-Dist: google-generativeai>=0.4.0
Dynamic: author
Dynamic: classifier
Dynamic: description
Dynamic: description-content-type
Dynamic: home-page
Dynamic: keywords
Dynamic: license
Dynamic: license-file
Dynamic: project-url
Dynamic: requires-dist
Dynamic: requires-python
Dynamic: summary
